sashimi/__init__.py
sashimi/__main__.py
sashimi_cli-0.0.8.dist-info/METADATA
sashimi_cli-0.0.8.dist-info/WHEEL
sashimi_cli-0.0.8.dist-info/entry_points.txt
sashimi_cli-0.0.8.dist-info/licenses/LICENSE
sashimi_cli-0.0.8.dist-info/RECORD
