Metadata-Version: 2.1
Name: sashimi-cli
Version: 0.0.8
Summary: CLI utility and python client package for Sashimi headless CMS
Project-URL: Homepage, https://github.com/yaroslaff/sashimi
Project-URL: Issues, https://github.com/yaroslaff/sashimi/issues
Author-email: Yaroslav Polyakov <yaroslaff@gmail.com>
License-File: LICENSE
Classifier: License :: OSI Approved :: MIT License
Classifier: Operating System :: OS Independent
Classifier: Programming Language :: Python :: 3
Requires-Python: >=3.9
Requires-Dist: python-dotenv
Requires-Dist: pyyaml
Requires-Dist: requests
Requires-Dist: rich==13.7.0
Requires-Dist: sqlalchemy
Requires-Dist: typer==0.9.0
Provides-Extra: mysql
Requires-Dist: mysqlclient; extra == 'mysql'
Provides-Extra: postgresql
Requires-Dist: psycopg2; extra == 'postgresql'
